src/__init__.py
src/complete_path.py
src/csv_time.py
src/day_activity.py
src/final_csv.py
src/group_activity.py
src/group_importance.py
src/group_priority.py
src/group_time.py
src/importance_activity.py
src/my_csv.py
src/personal_logging.py
src/priority.py
src/remove.py
src/row_importance.py
src/row_time.py
src/running.py
src/safe.py
src/source_csv.py
calculate_priority_activities-1.0.4.dist-info/LICENSE.md
calculate_priority_activities-1.0.4.dist-info/METADATA
calculate_priority_activities-1.0.4.dist-info/WHEEL
calculate_priority_activities-1.0.4.dist-info/entry_points.txt
calculate_priority_activities-1.0.4.dist-info/top_level.txt
calculate_priority_activities-1.0.4.dist-info/RECORD
