Metadata-Version: 2.1
Name: calculate-priority-activities
Version: 1.0.4
Summary: This script prints a file with the activities with their priority in the root directory
Home-page: http://github.com/alepuzio/calculate-priority-activities
Author: Alessandro Puzielli aka Alepuzio
Author-email: alessandro.puzielli@alepuzio.net
License: GPL 3
Platform: UNKNOWN
Classifier: Development Status :: 5 - Production/Stable
Classifier: License :: OSI Approved :: GNU General Public License v3 (GPLv3)
Classifier: Programming Language :: Python :: 3
Classifier: Topic :: Text Processing
Requires-Dist: markdown
